Metadata-Version: 2.1
Name: telr-payment
Version: 0.1.3.1
Summary: UNKNOWN
Home-page: https://github.com/alibigdeli/telr-payment-python
Author: Ali Bigdeli
Author-email: bigdeli.ali3@gmail.com
License: MIT
Project-URL: Github, https://github.com/alibigdeli/telr-payment-python
Project-URL: Author, https://alibigdeli.github.io/
Keywords: telr,payment,payment gateway,telr payment
Platform: UNKNOWN
Classifier: Development Status :: 5 - Production/Stable
Classifier: Intended Audience :: Developers
Classifier: License :: OSI Approved :: MIT License
Classifier: Environment :: Console
Classifier: Environment :: Web Environment
Classifier: Operating System :: Unix
Classifier: Operating System :: Microsoft :: Windows
Classifier: Programming Language :: Python
Classifier: Programming Language :: Python :: 3
Classifier: Programming Language :: Python :: 3.6
Classifier: Programming Language :: Python :: 3.7
Classifier: Programming Language :: Python :: 3.8
Classifier: Programming Language :: Python :: 3.9
Classifier: Programming Language :: Python :: 3.10
License-File: LICENSE.txt
